examples/__init__.py
examples/scripts/Update brondatabase json config files.ipynb
examples/wbd/afsluitmiddel_koppeling.py
examples/wbd/afwateringseenheden.py
examples/wbd/brug.py
examples/wbd/dwarsprofiel_xyz.py
examples/wbd/script write gml.py
examples/wbd/__pycache__/dwarsprofiel_xyz.cpython-37.pyc
examples/wbd/json/afsluitmiddel.json
examples/wbd/json/attribute_functions.py
examples/wbd/json/bodemval.json
examples/wbd/json/bodemval_stuw.json
examples/wbd/json/brug.json
examples/wbd/json/brug_dwp.json
examples/wbd/json/duikersifonhevel.json
examples/wbd/json/gemaal.json
examples/wbd/json/hydroobject.json
examples/wbd/json/meetlocatie.json
examples/wbd/json/pomp.json
examples/wbd/json/profiel_legger.json
examples/wbd/json/randvoorwaarden.json
examples/wbd/json/sturing.json
examples/wbd/json/stuw.json
examples/wbd/json/__pycache__/attribute_functions.cpython-37.pyc
examples/wbd/log/20220107_1355/logging.log
examples/wbd/log/20220107_1356/logging.log
examples/wbd/shape/mask.cpg
examples/wbd/shape/mask.dbf
examples/wbd/shape/mask.prj
examples/wbd/shape/mask.qix
examples/wbd/shape/mask.shp
examples/wbd/shape/mask.shp.xml
examples/wbd/shape/mask.shx
examples/wvv_notebook/Tutorial ToHyDAMOgml.ipynb
examples/wvv_notebook/Tutorial ToHyDAMOgml_antwoorden.ipynb
examples/wvv_notebook/gdb/Breg_Hydamo.gdb/NormGeparamProfiel.L10313.28596.16580.sr.lock
examples/wvv_notebook/gdb/Breg_Hydamo.gdb/_gdb.L10313.28596.16580.sr.lock
examples/wvv_notebook/gdb/Breg_Hydamo.gdb/a00000001.TablesByName.atx
examples/wvv_notebook/gdb/Breg_Hydamo.gdb/a00000001.freelist
examples/wvv_notebook/gdb/Breg_Hydamo.gdb/a00000001.gdbindexes
examples/wvv_notebook/gdb/Breg_Hydamo.gdb/a00000001.gdbtable
examples/wvv_notebook/gdb/Breg_Hydamo.gdb/a00000001.gdbtablx
examples/wvv_notebook/gdb/Breg_Hydamo.gdb/a00000002.gdbtable
examples/wvv_notebook/gdb/Breg_Hydamo.gdb/a00000002.gdbtablx
examples/wvv_notebook/gdb/Breg_Hydamo.gdb/a00000003.gdbindexes
examples/wvv_notebook/gdb/Breg_Hydamo.gdb/a00000003.gdbtable
tohydamogml-0.2.8.dist-info/LICENSE
tohydamogml-0.2.8.dist-info/METADATA
tohydamogml-0.2.8.dist-info/WHEEL
tohydamogml-0.2.8.dist-info/top_level.txt
tohydamogml-0.2.8.dist-info/RECORD
