Metadata-Version: 2.1
Name: tohydamogml
Version: 0.2.8
Summary: Convert DAMO filegdb export to gml
Home-page: UNKNOWN
Author: HaskoningDHV
Author-email: 
License: MIT
Keywords: DAMO HyDAMO GML
Platform: UNKNOWN
Classifier: Topic :: Scientific/Engineering :: Hydrology
Classifier: License :: Other/Proprietary License
Classifier: Programming Language :: Python :: 3
License-File: LICENSE
Requires-Dist: shapely
Requires-Dist: pyproj
Requires-Dist: rtree
Requires-Dist: lxml
Requires-Dist: geopandas
Requires-Dist: arcgis
